dbcollection/__init__.py
dbcollection/core/__init__.py
dbcollection/core/exceptions.py
dbcollection/core/loader.py
dbcollection/core/manager.py
dbcollection/core/api/__init__.py
dbcollection/core/api/add.py
dbcollection/core/api/cache.py
dbcollection/core/api/download.py
dbcollection/core/api/info.py
dbcollection/core/api/load.py
dbcollection/core/api/metadata.py
dbcollection/core/api/process.py
dbcollection/core/api/remove.py
dbcollection/datasets/__init__.py
dbcollection/datasets/caltech/__init__.py
dbcollection/datasets/caltech/caltech_pedestrian/__init__.py
dbcollection/datasets/caltech/caltech_pedestrian/detection.py
dbcollection/datasets/caltech/caltech_pedestrian/t.py
dbcollection/datasets/caltech/caltech_pedestrian/t1.py
dbcollection/datasets/cifar/__init__.py
dbcollection/datasets/cifar/cifar10/__init__.py
dbcollection/datasets/cifar/cifar10/classification.py
dbcollection/datasets/cifar/cifar100/__init__.py
dbcollection/datasets/cifar/cifar100/classification.py
dbcollection/datasets/coco/__init__.py
dbcollection/datasets/coco/captions.py
dbcollection/datasets/coco/detection.py
dbcollection/datasets/coco/keypoints.py
dbcollection/datasets/coco/load_data_test.py
dbcollection/datasets/flic/__init__.py
dbcollection/datasets/flic/keypoints.py
dbcollection/datasets/imagenet/__init__.py
dbcollection/datasets/imagenet/ilsvrc2012/__init__.py
dbcollection/datasets/imagenet/ilsvrc2012/classification.py
dbcollection/datasets/inria/__init__.py
dbcollection/datasets/inria/inria_pedestrian/__init__.py
dbcollection/datasets/inria/inria_pedestrian/detection.py
dbcollection/datasets/leeds_sports_pose/__init__.py
dbcollection/datasets/leeds_sports_pose/leeds_sports_pose/__init__.py
dbcollection/datasets/leeds_sports_pose/leeds_sports_pose/keypoints.py
dbcollection/datasets/leeds_sports_pose/leeds_sports_pose_extended/__init__.py
dbcollection/datasets/leeds_sports_pose/leeds_sports_pose_extended/keypoints.py
dbcollection-0.2.6.dist-info/DESCRIPTION.rst
dbcollection-0.2.6.dist-info/METADATA
dbcollection-0.2.6.dist-info/RECORD
dbcollection-0.2.6.dist-info/WHEEL
dbcollection-0.2.6.dist-info/metadata.json
dbcollection-0.2.6.dist-info/top_level.txt
