Metadata-Version: 2.0
Name: dbcollection
Version: 0.2.6
Summary: A collection of popular datasets for deep learning.
Home-page: https://github.com/dbcollection/dbcollection
Author: M. Farrajota
Author-email: UNKNOWN
License: MIT License
Download-URL: https://github.com/dbcollection/dbcollection/archive/0.2.6.tar.gz
Platform: any
Classifier: Development Status :: 3 - Alpha
Classifier: Environment :: MacOS X
Classifier: Environment :: Win32 (MS Windows)
Classifier: Environment :: X11 Applications
Classifier: Intended Audience :: Developers
Classifier: Intended Audience :: Science/Research
Classifier: Topic :: Scientific/Engineering
Classifier: License :: OSI Approved :: MIT License
Classifier: Operating System :: MacOS :: MacOS X
Classifier: Operating System :: Microsoft :: Windows
Classifier: Operating System :: POSIX :: Linux
Classifier: Programming Language :: Python
Classifier: Programming Language :: Python :: 2
Classifier: Programming Language :: Python :: 2.7
Classifier: Programming Language :: Python :: 3
Classifier: Programming Language :: Python :: 3.5
Classifier: Programming Language :: Python :: 3.6
Requires-Dist: certifi (==2018.4.16)
Requires-Dist: chardet (==3.0.4)
Requires-Dist: h5py (==2.7.1)
Requires-Dist: idna (==2.6)
Requires-Dist: numpy (==1.14.3)
Requires-Dist: patool (==1.12)
Requires-Dist: pillow (==5.1.0)
Requires-Dist: progressbar2 (==3.37.1)
Requires-Dist: python-utils (==2.3.0)
Requires-Dist: requests (==2.18.4)
Requires-Dist: scipy (==1.1.0)
Requires-Dist: six (==1.11.0)
Requires-Dist: urllib3 (==1.22)
Requires-Dist: xmltodict (==0.11.0)
